[
  {
    "name": "Nasi Dadar Cumi",
    "price": 0,
    "quantity": 0,
    "capital": 0
  },
  {
    "name": "Nasi Dadar Ayam",
    "price": 0,
    "quantity": 0,
    "capital": 0
  },
  {
    "name": "Nasi Dadar Tongkol",
    "price": 0,
    "quantity": 0,
    "capital": 0
  },
  {
    "name": "Nasi Dadar Ori",
    "price": 0,
    "quantity": 0,
    "capital": 0
  },
  {
    "name": "Nasi Dadar Bakar Cumi (Bakar)",
    "price": 0,
    "quantity": 0,
    "capital": 0
  },
  {
    "name": "Nasi Dadar Bakar Ayam (Bakar)",
    "price": 0,
    "quantity": 0,
    "capital": 0
  },
  {
    "name": "Nasi Dadar Bakar Ori (Bakar)",
    "price": 0,
    "quantity": 0,
    "capital": 0
  },
  {
    "name": "Nasi Dadar (Bakar)",
    "price": 0,
    "quantity": 0,
    "capital": 0
  },
  {
    "name": "Paket Hemat Cumi (Es Teh)",
    "price": 0,
    "quantity": 0,
    "capital": 0
  },
  {
    "name": "Paket Hemat Ayam (Es Teh)",
    "price": 0,
    "quantity": 0,
    "capital": 0
  },
  {
    "name": "Paket Hemat Bakar Cumi + Es Teh",
    "price": 0,
    "quantity": 0,
    "capital": 0
  },
  {
    "name": "Paket Hemat Bakar Ayam + Es Teh",
    "price": 0,
    "quantity": 0,
    "capital": 0
  },
  {
    "name": "Sambal Cumi",
    "price": 0,
    "quantity": 0,
    "capital": 0
  },
  {
    "name": "Sambal Tongkol",
    "price": 0,
    "quantity": 0,
    "capital": 0
  },
  {
    "name": "Sambal Ayam",
    "price": 0,
    "quantity": 0,
    "capital": 0
  },
  {
    "name": "Es Teh",
    "price": 0,
    "quantity": 0,
    "capital": 0
  },
  {
    "name": "Es Jeruk",
    "price": 0,
    "quantity": 0,
    "capital": 0
  },
  {
    "name": "Nasi Putih",
    "price": 0,
    "quantity": 0,
    "capital": 0
  }
]
